mkdocs_export_confluence/__init__.py
mkdocs_export_confluence/plugin.py
mkdocs_export_confluence-0.1.2.dist-info/METADATA
mkdocs_export_confluence-0.1.2.dist-info/WHEEL
mkdocs_export_confluence-0.1.2.dist-info/entry_points.txt
mkdocs_export_confluence-0.1.2.dist-info/top_level.txt
mkdocs_export_confluence-0.1.2.dist-info/RECORD
